ttt/__init__.py
ttt/exporter.py
ttt/saved_model_export.py
ttt/sk_inference.py
ttt/sklearn_helper.py
ttt/tf_helper.py
ttt/tf_tree_inference.py
ttt/tf_utils.py
ttt/weight_utils.py
ttt/xgb_inference.py
TFTree-0.1.8.dist-info/METADATA
TFTree-0.1.8.dist-info/WHEEL
TFTree-0.1.8.dist-info/top_level.txt
TFTree-0.1.8.dist-info/RECORD
