Metadata-Version: 2.1
Name: TFTree
Version: 0.1.8
Summary: Tree to tensorflow
Home-page: https://github.com/yupbank/tree_to_tensorflow
Author: Peng Yu
Author-email: yupbank@gmail.com
License: UNKNOWN
Download-URL: https://github.com/yupbank/tree_to_tensorflow/archive/0.1.8.tar.gz
Keywords: tensorflow,machine learning,sklearn,spark,model-serving,xgboost
Platform: UNKNOWN
Requires-Dist: tensorflow
Requires-Dist: scipy (>=0.17)
Requires-Dist: numpy (>=1.10)
Requires-Dist: scikit-learn (>=0.20.2)
